[ {
  "learningObject" : "Final Project - Grade",
  "conceptIds" : [ ],
  "dataImportance" : 1.0
}, {
  "learningObject" : "Reflection1 – Then and Now",
  "conceptIds" : [ ],
  "dataImportance" : 1.0
}, {
  "learningObject" : "Lab1 - Page One",
  "conceptIds" : [ ],
  "dataImportance" : 1.0
}, {
  "learningObject" : "Lab2 – Profile – HTML",
  "conceptIds" : [ ],
  "dataImportance" : 1.0
}, {
  "learningObject" : "Lab3 – Profile – Style and Layout ",
  "conceptIds" : [ ],
  "dataImportance" : 1.0
}, {
  "learningObject" : "Reflection #2 – Mid-Term Project Postmortem",
  "conceptIds" : [ ],
  "dataImportance" : 1.0
}, {
  "learningObject" : "Lab4 – Interactive Components",
  "conceptIds" : [ ],
  "dataImportance" : 1.0
}, {
  "learningObject" : "Lab5 – Site Theme",
  "conceptIds" : [ ],
  "dataImportance" : 1.0
}, {
  "learningObject" : "Lab6 – Responsive Elements",
  "conceptIds" : [ ],
  "dataImportance" : 1.0
}, {
  "learningObject" : "Reflection#3 – Course Reflection",
  "conceptIds" : [ ],
  "dataImportance" : 1.0
}, {
  "learningObject" : "Mid-Term - Project Grade",
  "conceptIds" : [ ],
  "dataImportance" : 1.0
}, {
  "learningObject" : "Course Grade",
  "conceptIds" : [ ],
  "dataImportance" : 1.0
} ]